{
    "TestScenario.Server": {
        "count": 12005,
        "good_items": 0,
        "mean": 27.671123440410668,
        "percentiles": {
            "50.0": 27.761842894,
            "80.0": 43.8781173224,
            "90.0": 49.7348256774,
            "95.0": 52.286192022,
            "99.0": 54.472170695639996,
            "99.9": 55.09470908162404
        },
        "qps": 104.54520903129851,
        "took": 114.8307044506073,
        "total_items": 12005
    },
    "cmdline": "Namespace(accuracy=False, backend='tfserving', cache=0, cache_dir=None, count=None, data_format=None, dataset='imagenet_tfserving', dataset_list=None, dataset_path='data_imagenet', deployment_name='image', find_peak_performance=False, inputs=None, max_batchsize=32, max_latency=80.0, mlperf_conf='../../mlperf.conf', model=None, model_name='resnet50', namespace='resnet-tf-single', output='output-O/cpumemory-resnet-1-32-S-1-3', outputs=None, preprocess=0, profile=None, qps=200, samples_per_query=None, scenario='Server', server='172.30.0.50:31930', threads=256, time=None, user_conf='user.conf')",
    "runtime": "tfserving",
    "time": 1666386002,
    "version": "2.9.2/v2.9.1-132-g18960c44ad3"
}