{
    "TestScenario.Server": {
        "count": 12005,
        "good_items": 0,
        "mean": 11.710133017099293,
        "percentiles": {
            "50.0": 11.812293584,
            "80.0": 17.672646113200006,
            "90.0": 19.968001802,
            "95.0": 20.9199509798,
            "99.0": 22.056387803599982,
            "99.9": 22.857290627792008
        },
        "qps": 145.01796084330525,
        "took": 82.78284931182861,
        "total_items": 12005
    },
    "cmdline": "Namespace(accuracy=False, backend='tfserving', cache=0, cache_dir=None, count=None, data_format=None, dataset='imagenet_tfserving', dataset_list=None, dataset_path='data_imagenet', deployment_name='image', find_peak_performance=False, inputs=None, max_batchsize=32, max_latency=None, mlperf_conf='../../mlperf.conf', model=None, model_name='resnet50', namespace='resnet-tf-single', output='exp1-server/none-resnet-16-32-S-1-2', outputs=None, preprocess=0, profile=None, qps=200, samples_per_query=None, scenario='Server', server='172.30.0.50:31930', threads=256, time=None, user_conf='user.conf')",
    "runtime": "tfserving",
    "time": 1665742536,
    "version": "2.9.2/v2.9.1-132-g18960c44ad3"
}