{
    "TestScenario.Offline": {
        "count": 24576,
        "good_items": 0,
        "mean": 81.94699386785221,
        "percentiles": {
            "50.0": 81.997565578,
            "80.0": 130.70816817,
            "90.0": 146.92706401,
            "95.0": 154.882827424,
            "99.0": 161.304589392,
            "99.9": 162.782019702
        },
        "qps": 150.73082267760566,
        "took": 163.04561710357666,
        "total_items": 24576
    },
    "cmdline": "Namespace(accuracy=False, backend='tfserving', cache=0, cache_dir=None, count=None, data_format=None, dataset='imagenet_tfserving', dataset_list=None, dataset_path='data_imagenet', deployment_name='image', find_peak_performance=False, inputs=None, max_batchsize=4, max_latency=None, mlperf_conf='../../mlperf.conf', model=None, model_name='resnet50', namespace='resnet-tf-single', output='output-exp1/none-resnet-4-0-O-4-10', outputs=None, preprocess=0, profile=None, qps=None, samples_per_query=None, scenario='Offline', server='172.30.0.50:31930', threads=36, time=None, user_conf='user.conf')",
    "runtime": "tfserving",
    "time": 1662654296,
    "version": "2.4.1/v2.4.0-49-g85c8b2a817f"
}