{
    "TestScenario.Offline": {
        "count": 24576,
        "good_items": 0,
        "mean": 65.58849664511239,
        "percentiles": {
            "50.0": 65.569767245,
            "80.0": 104.086977839,
            "90.0": 116.954191136,
            "95.0": 123.328243998,
            "99.0": 128.41419982275,
            "99.9": 128.785642489
        },
        "qps": 190.7622356496771,
        "took": 128.83053040504456,
        "total_items": 24576
    },
    "cmdline": "Namespace(accuracy=False, backend='tfserving', cache=0, cache_dir=None, count=None, data_format=None, dataset='imagenet_tfserving', dataset_list=None, dataset_path='data_imagenet', deployment_name='image', find_peak_performance=False, inputs=None, max_batchsize=10, max_latency=None, mlperf_conf='../../mlperf.conf', model=None, model_name='resnet50', namespace='resnet-tf-single', output='output-exp10/cpumem-resnet-2-0-O-10-10', outputs=None, preprocess=0, profile=None, qps=None, samples_per_query=None, scenario='Offline', server='172.30.0.50:31930', threads=36, time=None, user_conf='user.conf')",
    "runtime": "tfserving",
    "time": 1663791172,
    "version": "2.4.1/v2.4.0-49-g85c8b2a817f"
}