{
    "TestScenario.Server": {
        "count": 12005,
        "good_items": 0,
        "mean": 4.778433373087214,
        "percentiles": {
            "50.0": 4.756243926,
            "80.0": 6.925235184400001,
            "90.0": 7.7479135934,
            "95.0": 8.1953108598,
            "99.0": 9.295725891159996,
            "99.9": 10.531899402168046
        },
        "qps": 171.28809316621405,
        "took": 70.08659958839417,
        "total_items": 12005
    },
    "cmdline": "Namespace(accuracy=False, backend='tfserving', cache=0, cache_dir=None, count=None, data_format=None, dataset='imagenet_tfserving', dataset_list=None, dataset_path='data_imagenet', deployment_name='image', find_peak_performance=False, inputs=None, max_batchsize=32, max_latency=None, mlperf_conf='../../mlperf.conf', model=None, model_name='resnet50', namespace='resnet-tf-single', output='exp1-server/cpumemory-resnet-16-32-S-1-9', outputs=None, preprocess=0, profile=None, qps=200, samples_per_query=None, scenario='Server', server='172.30.0.50:31930', threads=256, time=None, user_conf='user.conf')",
    "runtime": "tfserving",
    "time": 1665755132,
    "version": "2.9.2/v2.9.1-132-g18960c44ad3"
}