{
    "TestScenario.Offline": {
        "count": 32768,
        "good_items": 0,
        "mean": 109.34193568919916,
        "percentiles": {
            "50.0": 109.14119281149999,
            "80.0": 174.79419704680004,
            "90.0": 196.86794872619998,
            "95.0": 207.85545134499998,
            "99.0": 216.50552953797998,
            "99.9": 218.96613449430205
        },
        "qps": 149.3301253941695,
        "took": 219.43328523635864,
        "total_items": 32768
    },
    "cmdline": "Namespace(accuracy=False, backend='tfserving', cache=0, cache_dir=None, count=None, data_format=None, dataset='imagenet_tfserving', dataset_list=None, dataset_path='data_imagenet', deployment_name='image', find_peak_performance=False, inputs=None, max_batchsize=1, max_latency=None, mlperf_conf='../../mlperf.conf', model=None, model_name='resnet50', namespace='resnet-tf-single', output='output-O/none-resnet-2-32-O-1-2', outputs=None, preprocess=0, profile=None, qps=200, samples_per_query=None, scenario='Offline', server='172.30.0.50:31930', threads=256, time=None, user_conf='user.conf')",
    "runtime": "tfserving",
    "time": 1666691099,
    "version": "2.9.2/v2.9.1-132-g18960c44ad3"
}