{
    "TestScenario.Offline": {
        "count": 32768,
        "good_items": 0,
        "mean": 91.0389167319795,
        "percentiles": {
            "50.0": 91.1717324505,
            "80.0": 143.294323222,
            "90.0": 160.5664522,
            "95.0": 169.15399861,
            "99.0": 174.787051534,
            "99.9": 175.740281777
        },
        "qps": 186.40137130717494,
        "took": 175.79269814491272,
        "total_items": 32768
    },
    "cmdline": "Namespace(accuracy=False, backend='tfserving', cache=0, cache_dir=None, count=None, data_format=None, dataset='imagenet_tfserving', dataset_list=None, dataset_path='data_imagenet', deployment_name='image', find_peak_performance=False, inputs=None, max_batchsize=32, max_latency=None, mlperf_conf='../../mlperf.conf', model=None, model_name='resnet50', namespace='resnet-tf-single', output='output-O/cpumemory-resnet-2-32-O-32-1', outputs=None, preprocess=0, profile=None, qps=200, samples_per_query=None, scenario='Offline', server='172.30.0.50:31930', threads=256, time=None, user_conf='user.conf')",
    "runtime": "tfserving",
    "time": 1666700110,
    "version": "2.9.2/v2.9.1-132-g18960c44ad3"
}