{
    "TestScenario.Server": {
        "count": 12005,
        "good_items": 0,
        "mean": 28.080731169317957,
        "percentiles": {
            "50.0": 28.059576798,
            "80.0": 44.5018994534,
            "90.0": 50.4973589772,
            "95.0": 53.1839279432,
            "99.0": 55.311086348159996,
            "99.9": 55.879332521652024
        },
        "qps": 103.70153541279113,
        "took": 115.76492047309875,
        "total_items": 12005
    },
    "cmdline": "Namespace(accuracy=False, backend='tfserving', cache=0, cache_dir=None, count=None, data_format=None, dataset='imagenet_tfserving', dataset_list=None, dataset_path='data_imagenet', deployment_name='image', find_peak_performance=False, inputs=None, max_batchsize=32, max_latency=None, mlperf_conf='../../mlperf.conf', model=None, model_name='resnet50', namespace='resnet-tf-single', output='exp1/cpumemory-resnet-1-32-S-1-1', outputs=None, preprocess=0, profile=None, qps=200, samples_per_query=None, scenario='Server', server='172.30.0.50:31930', threads=256, time=None, user_conf='user.conf')",
    "runtime": "tfserving",
    "time": 1665967315,
    "version": "2.9.2/v2.9.1-132-g18960c44ad3"
}