{
    "TestScenario.Offline": {
        "count": 32768,
        "good_items": 0,
        "mean": 35.91858198652222,
        "percentiles": {
            "50.0": 33.801147663500004,
            "80.0": 58.429868121,
            "90.0": 66.681981493,
            "95.0": 70.829873067,
            "99.0": 79.17076224832995,
            "99.9": 81.827090509
        },
        "qps": 400.02462531226547,
        "took": 81.91495704650879,
        "total_items": 32768
    },
    "cmdline": "Namespace(accuracy=False, backend='tfserving', cache=0, cache_dir=None, count=None, data_format=None, dataset='imagenet_tfserving', dataset_list=None, dataset_path='data_imagenet', deployment_name='image', find_peak_performance=False, inputs=None, max_batchsize=4, max_latency=None, mlperf_conf='../../mlperf.conf', model=None, model_name='resnet50', namespace='resnet-tf-single', output='exp3/cpumemory-resnet-1-32-O-4-3', outputs=None, preprocess=0, profile=None, qps=200, samples_per_query=None, scenario='Offline', server='172.30.0.50:31930', threads=256, time=None, user_conf='user.conf')",
    "runtime": "tfserving",
    "time": 1667524471,
    "version": "2.9.2/v2.9.1-132-g18960c44ad3"
}